[
  {
    "id": "9ND0CG3LM22K",
    "name": "A Plague Tale: Innocence - Windows 10",
    "url": "https://www.microsoft.com/en-us/store/p/a-plague-tale-innocence---windows-10/9ND0CG3LM22K",
    "availability": {
      "console": false,
      "pc": true
    }
  },
  {
    "id": "9NJWTJSVGVLJ",
    "name": "Age of Empires Definitive Edition",
    "url": "https://www.microsoft.com/en-us/store/p/age-of-empires-definitive-edition/9NJWTJSVGVLJ",
    "availability": {
      "console": false,
      "pc": true
    }
  },
  {
    "id": "9NJDD0JGPP2Q",
    "name": "Age of Empires II: Definitive Edition",
    "url": "https://www.microsoft.com/en-us/store/p/age-of-empires-ii-definitive-edition/9NJDD0JGPP2Q",
    "availability": {
      "console": false,
      "pc": true
    }
  },
  {
    "id": "9N1HF804QXN4",
    "name": "Age of Empires III: Definitive Edition",
    "url": "https://www.microsoft.com/en-us/store/p/age-of-empires-iii-definitive-edition/9N1HF804QXN4",
    "availability": {
      "console": false,
      "pc": true
    }
  },
  {
    "id": "9MZ2B3W86SCK",
    "name": "Age of Wonders: Planetfall",
    "url": "https://www.microsoft.com/en-us/store/p/age-of-wonders-planetfall/9MZ2B3W86SCK",
    "availability": {
      "console": false,
      "pc": true
    }
  },
  {
    "id": "9NKV44QF1R68",
    "name": "Alan Wake",
    "url": "https://www.microsoft.com/en-us/store/p/alan-wake/9NKV44QF1R68",
    "availability": {
      "console": false,
      "pc": true
    }
  },
  {
    "id": "9NSRJ872SGH7",
    "name": "Alien: Isolation",
    "url": "https://www.microsoft.com/en-us/store/p/alien-isolation/9NSRJ872SGH7",
    "availability": {
      "console": false,
      "pc": true
    }
  },
  {
    "id": "9MVJGBNNFPPS",
    "name": "Alvastia Chronicles",
    "url": "https://www.microsoft.com/en-us/store/p/alvastia-chronicles/9MVJGBNNFPPS",
    "availability": {
      "console": true,
      "pc": true
    }
  },
  {
    "id": "9NR6DZ9F76P8",
    "name": "Ape Out",
    "url": "https://www.microsoft.com/en-us/store/p/ape-out/9NR6DZ9F76P8",
    "availability": {
      "console": false,
      "pc": true
    }
  },
  {
    "id": "9NBLGGH52XC6",
    "name": "ARK: Survival Evolved",
    "url": "https://www.microsoft.com/en-us/store/p/ark-survival-evolved/9NBLGGH52XC6",
    "availability": {
      "console": false,
      "pc": true
    }
  },
  {
    "id": "9NFT0CMC62DX",
    "name": "Astrologaster",
    "url": "https://www.microsoft.com/en-us/store/p/astrologaster/9NFT0CMC62DX",
    "availability": {
      "console": false,
      "pc": true
    }
  },
  {
    "id": "9NBLGGH43KZB",
    "name": "ASTRONEER",
    "url": "https://www.microsoft.com/en-us/store/p/astroneer/9NBLGGH43KZB",
    "availability": {
      "console": true,
      "pc": true
    }
  },
  {
    "id": "9N4T8VCMQVDT",
    "name": "Bad North: Jotunn Edition",
    "url": "https://www.microsoft.com/en-us/store/p/bad-north-jotunn-edition/9N4T8VCMQVDT",
    "availability": {
      "console": false,
      "pc": true
    }
  },
  {
    "id": "9NT8XR7D5L00",
    "name": "Battle Chasers: Nightwar",
    "url": "https://www.microsoft.com/en-us/store/p/battle-chasers-nightwar/9NT8XR7D5L00",
    "availability": {
      "console": false,
      "pc": true
    }
  },
  {
    "id": "9NGWKW55M85P",
    "name": "Battlefleet Gothic: Armada 2 - Windows 10",
    "url": "https://www.microsoft.com/en-us/store/p/battlefleet-gothic-armada-2---windows-10/9NGWKW55M85P",
    "availability": {
      "console": false,
      "pc": true
    }
  },
  {
    "id": "9NQVDQS2BC10",
    "name": "BATTLETECH",
    "url": "https://www.microsoft.com/en-us/store/p/battletech/9NQVDQS2BC10",
    "availability": {
      "console": false,
      "pc": true
    }
  },
  {
    "id": "9N7GCF5SGCXC",
    "name": "Battletoads",
    "url": "https://www.microsoft.com/en-us/store/p/battletoads/9N7GCF5SGCXC",
    "availability": {
      "console": true,
      "pc": true
    }
  },
  {
    "id": "9NG7LG421V0Q",
    "name": "Blair Witch",
    "url": "https://www.microsoft.com/en-us/store/p/blair-witch/9NG7LG421V0Q",
    "availability": {
      "console": true,
      "pc": true
    }
  },
  {
    "id": "9NX6XGVJ0J3D",
    "name": "Bleeding Edge",
    "url": "https://www.microsoft.com/en-us/store/p/bleeding-edge/9NX6XGVJ0J3D",
    "availability": {
      "console": true,
      "pc": true
    }
  },
  {
    "id": "9MWB2BFF0SPD",
    "name": "Bloodstained: Ritual of the Night",
    "url": "https://www.microsoft.com/en-us/store/p/bloodstained-ritual-of-the-night/9MWB2BFF0SPD",
    "availability": {
      "console": false,
      "pc": true
    }
  },
  {
    "id": "9PDXF172R7VJ",
    "name": "Bridge Constructor Portal",
    "url": "https://www.microsoft.com/en-us/store/p/bridge-constructor-portal/9PDXF172R7VJ",
    "availability": {
      "console": false,
      "pc": true
    }
  },
  {
    "id": "9P03ZQMBMV65",
    "name": "Broforce",
    "url": "https://www.microsoft.com/en-us/store/p/broforce/9P03ZQMBMV65",
    "availability": {
      "console": false,
      "pc": true
    }
  },
  {
    "id": "9MSMJH3C6TKR",
    "name": "Carrion",
    "url": "https://www.microsoft.com/en-us/store/p/carrion/9MSMJH3C6TKR",
    "availability": {
      "console": false,
      "pc": true
    }
  },
  {
    "id": "9P675WH90SB4",
    "name": "Children of Morta",
    "url": "https://www.microsoft.com/en-us/store/p/children-of-morta/9P675WH90SB4",
    "availability": {
      "console": true,
      "pc": true
    }
  },
  {
    "id": "9NWVC7XP3PFD",
    "name": "Cities: Skylines - Windows 10 Edition",
    "url": "https://www.microsoft.com/en-us/store/p/cities-skylines---windows-10-edition/9NWVC7XP3PFD",
    "availability": {
      "console": false,
      "pc": true
    }
  },
  {
    "id": "9N8WVMD7J5GQ",
    "name": "Clustertruck",
    "url": "https://www.microsoft.com/en-us/store/p/clustertruck/9N8WVMD7J5GQ",
    "availability": {
      "console": false,
      "pc": true
    }
  },
  {
    "id": "9NXR6469DM2P",
    "name": "Crackdown 3",
    "url": "https://www.xbox.com/en-us/games/crackdown-3",
    "availability": {
      "console": true,
      "pc": true
    }
  },
  {
    "id": "9P3SWZZJ1M4B",
    "name": "Creature in the Well",
    "url": "https://www.microsoft.com/en-us/store/p/creature-in-the-well/9P3SWZZJ1M4B",
    "availability": {
      "console": true,
      "pc": true
    }
  },
  {
    "id": "9NFDPQ0KZ6RN",
    "name": "CrossCode",
    "url": "https://www.microsoft.com/en-us/store/p/crosscode/9NFDPQ0KZ6RN",
    "availability": {
      "console": false,
      "pc": true
    }
  },
  {
    "id": "9PD1Z95CNTW4",
    "name": "Crossing Souls",
    "url": "https://www.microsoft.com/en-us/store/p/crossing-souls/9PD1Z95CNTW4",
    "availability": {
      "console": false,
      "pc": true
    }
  },
  {
    "id": "9N7GG222GTTH",
    "name": "Crusader Kings III",
    "url": "https://www.microsoft.com/en-us/store/p/crusader-kings-iii/9N7GG222GTTH",
    "availability": {
      "console": false,
      "pc": true
    }
  },
  {
    "id": "9NJ5X04M30HN",
    "name": "Darksiders Genesis",
    "url": "https://www.microsoft.com/en-us/store/p/darksiders-genesis/9NJ5X04M30HN",
    "availability": {
      "console": false,
      "pc": true
    }
  },
  {
    "id": "9PLPXGK1GDQ1",
    "name": "Darksiders III",
    "url": "https://www.microsoft.com/en-us/store/p/darksiders-iii/9PLPXGK1GDQ1",
    "availability": {
      "console": false,
      "pc": true
    }
  },
  {
    "id": "9NMS4SFNBGBH",
    "name": "Dead by Daylight Windows",
    "url": "https://www.microsoft.com/en-us/store/p/dead-by-daylight-windows/9NMS4SFNBGBH",
    "availability": {
      "console": false,
      "pc": true
    }
  },
  {
    "id": "9NKVX66J0ZSK",
    "name": "Dead Cells",
    "url": "https://www.microsoft.com/en-us/store/p/dead-cells/9NKVX66J0ZSK",
    "availability": {
      "console": false,
      "pc": true
    }
  },
  {
    "id": "9MV537XVLVXR",
    "name": "Death's Gambit",
    "url": "https://www.microsoft.com/en-us/store/p/deaths-gambit/9MV537XVLVXR",
    "availability": {
      "console": false,
      "pc": true
    }
  },
  {
    "id": "9PF6BS5DGNLX",
    "name": "Deliver Us The Moon.",
    "url": "https://www.microsoft.com/en-us/store/p/deliver-us-the-moon/9PF6BS5DGNLX",
    "availability": {
      "console": false,
      "pc": true
    }
  },
  {
    "id": "9N5344N0TFR7",
    "name": "DEMON'S TILT",
    "url": "https://www.microsoft.com/en-us/store/p/demons-tilt/9N5344N0TFR7",
    "availability": {
      "console": true,
      "pc": true
    }
  },
  {
    "id": "C37XBX7DCBZ0",
    "name": "Descenders",
    "url": "https://www.microsoft.com/en-us/store/p/descenders/C37XBX7DCBZ0",
    "availability": {
      "console": true,
      "pc": true
    }
  },
  {
    "id": "9MT31ZWMPJCK",
    "name": "DiRT Rally 2.0 (Windows)",
    "url": "https://www.microsoft.com/en-us/store/p/dirt-rally-20-windows/9MT31ZWMPJCK",
    "availability": {
      "console": false,
      "pc": true
    }
  },
  {
    "id": "9MW4RJDRSF78",
    "name": "Dishonored 2",
    "url": "https://www.microsoft.com/en-us/store/p/dishonored-2/9MW4RJDRSF78",
    "availability": {
      "console": false,
      "pc": true
    }
  },
  {
    "id": "9N6Z8DQXSQWH",
    "name": "Disneyland Adventures",
    "url": "https://www.microsoft.com/en-us/store/p/disneyland-adventures/9N6Z8DQXSQWH",
    "availability": {
      "console": true,
      "pc": true
    }
  },
  {
    "id": "C0XBNVR137DZ",
    "name": "Don't Starve: Giant Edition",
    "url": "https://www.microsoft.com/en-us/store/p/dont-starve-giant-edition/C0XBNVR137DZ",
    "availability": {
      "console": true,
      "pc": true
    }
  },
  {
    "id": "9NJPT63K27W8",
    "name": "Double Kick Heroes",
    "url": "https://www.microsoft.com/en-us/store/p/double-kick-heroes/9NJPT63K27W8",
    "availability": {
      "console": true,
      "pc": true
    }
  },
  {
    "id": "9P641Z19NT2S",
    "name": "Downwell",
    "url": "https://www.microsoft.com/en-us/store/p/downwell/9P641Z19NT2S",
    "availability": {
      "console": false,
      "pc": true
    }
  },
  {
    "id": "9PBDC0XZ8TXK",
    "name": "DRAGON QUEST® XI S: Echoes of an Elusive Age™ - Definitive Edition",
    "url": "https://www.microsoft.com/en-us/store/p/dragon-quest-xi-s-echoes-of-an-elusive-age---definitive-edition/9PBDC0XZ8TXK",
    "availability": {
      "console": true,
      "pc": true
    }
  },
  {
    "id": "9N46K0X6TBZK",
    "name": "Dungeon of the Endless™",
    "url": "https://www.microsoft.com/en-us/store/p/dungeon-of-the-endless/9N46K0X6TBZK",
    "availability": {
      "console": false,
      "pc": true
    }
  },
  {
    "id": "9NP09BFQNHCJ",
    "name": "Endless Legend",
    "url": "https://www.microsoft.com/en-us/store/p/endless-legend/9NP09BFQNHCJ",
    "availability": {
      "console": false,
      "pc": true
    }
  },
  {
    "id": "9NV3Q7WVN2RB",
    "name": "Endless Space 2: Deluxe Edition",
    "url": "https://www.microsoft.com/en-us/store/p/endless-space-2-deluxe-edition/9NV3Q7WVN2RB",
    "availability": {
      "console": false,
      "pc": true
    }
  },
  {
    "id": "9NB65S6LFZRT",
    "name": "Enter The Gungeon",
    "url": "https://www.microsoft.com/en-us/store/p/enter-the-gungeon/9NB65S6LFZRT",
    "availability": {
      "console": true,
      "pc": true
    }
  },
  {
    "id": "9PHQJWGLTZM8",
    "name": "Europa Universalis IV - Microsoft Store Edition",
    "url": "https://www.microsoft.com/en-us/store/p/europa-universalis-iv---microsoft-store-edition/9PHQJWGLTZM8",
    "availability": {
      "console": false,
      "pc": true
    }
  },
  {
    "id": "9NL9VGSH00LL",
    "name": "F1® 2019 PC",
    "url": "https://www.microsoft.com/en-us/store/p/f1-2019-pc/9NL9VGSH00LL",
    "availability": {
      "console": false,
      "pc": true
    }
  },
  {
    "id": "9N1XLJGDC163",
    "name": "Faeria",
    "url": "https://www.microsoft.com/en-us/store/p/faeria/9N1XLJGDC163",
    "availability": {
      "console": false,
      "pc": true
    }
  },
  {
    "id": "9NKGNMNK3K3Z",
    "name": "Fallout 76 (PC)",
    "url": "https://www.microsoft.com/en-us/store/p/fallout-76-pc/9NKGNMNK3K3Z",
    "availability": {
      "console": false,
      "pc": true
    }
  },
  {
    "id": "9N2NCBXW44HV",
    "name": "Farming Simulator 17 - Windows 10",
    "url": "https://www.microsoft.com/en-us/store/p/farming-simulator-17---windows-10/9N2NCBXW44HV",
    "availability": {
      "console": false,
      "pc": true
    }
  },
  {
    "id": "9MVNB889L3HN",
    "name": "Felix The Reaper PC",
    "url": "https://www.microsoft.com/en-us/store/p/felix-the-reaper-pc/9MVNB889L3HN",
    "availability": {
      "console": false,
      "pc": true
    }
  },
  {
    "id": "9NPGTNQFC8B5",
    "name": "FINAL FANTASY IX",
    "url": "https://www.microsoft.com/en-us/store/p/final-fantasy-ix/9NPGTNQFC8B5",
    "availability": {
      "console": true,
      "pc": true
    }
  },
  {
    "id": "9PN0W216SKZB",
    "name": "FINAL FANTASY VII WINDOWS EDITION",
    "url": "https://www.microsoft.com/en-us/store/p/final-fantasy-vii-windows-edition/9PN0W216SKZB",
    "availability": {
      "console": false,
      "pc": true
    }
  },
  {
    "id": "9NR0N2LZ6TC5",
    "name": "FINAL FANTASY XV WINDOWS EDITION",
    "url": "https://www.microsoft.com/en-us/store/p/final-fantasy-xv-windows-edition/9NR0N2LZ6TC5",
    "availability": {
      "console": false,
      "pc": true
    }
  },
  {
    "id": "9NM7LC8MJXKS",
    "name": "Fishing Sim World®: Pro Tour",
    "url": "https://www.microsoft.com/en-us/store/p/fishing-sim-world-pro-tour/9NM7LC8MJXKS",
    "availability": {
      "console": false,
      "pc": true
    }
  },
  {
    "id": "9N0K062BZJVK",
    "name": "Football Manager 2020",
    "url": "https://www.microsoft.com/en-us/store/p/football-manager-2020/9N0K062BZJVK",
    "availability": {
      "console": false,
      "pc": true
    }
  },
  {
    "id": "9NS1CD1V4BKW",
    "name": "For The King",
    "url": "https://www.microsoft.com/en-us/store/p/for-the-king/9NS1CD1V4BKW",
    "availability": {
      "console": false,
      "pc": true
    }
  },
  {
    "id": "9P5SFDNW6V13",
    "name": "Forager",
    "url": "https://www.microsoft.com/en-us/store/p/forager/9P5SFDNW6V13",
    "availability": {
      "console": false,
      "pc": true
    }
  },
  {
    "id": "9PNJXVCVWD4K",
    "name": "Forza Horizon 4 Standard Edition",
    "url": "https://www.xbox.com/en-us/games/forza-horizon-4",
    "availability": {
      "console": true,
      "pc": true
    }
  },
  {
    "id": "9NS0KH25D76X",
    "name": "Frostpunk",
    "url": "https://www.microsoft.com/en-us/store/p/frostpunk/9NS0KH25D76X",
    "availability": {
      "console": false,
      "pc": true
    }
  },
  {
    "id": "9NWNTZQW4G8G",
    "name": "FTL: Faster Than Light",
    "url": "https://www.microsoft.com/en-us/store/p/ftl-faster-than-light/9NWNTZQW4G8G",
    "availability": {
      "console": false,
      "pc": true
    }
  },
  {
    "id": "9PBJQ90CT236",
    "name": "Gato Roboto",
    "url": "https://www.microsoft.com/en-us/store/p/gato-roboto/9PBJQ90CT236",
    "availability": {
      "console": false,
      "pc": true
    }
  },
  {
    "id": "C2KDNLT2H7DM",
    "name": "Gears 5",
    "url": "https://www.xbox.com/en-us/games/gears-5",
    "availability": {
      "console": true,
      "pc": true
    }
  },
  {
    "id": "9P9CKRGR40KK",
    "name": "Gears 5 Ultimate Edition",
    "url": "https://www.microsoft.com/en-us/store/p/gears-5-ultimate-edition/9P9CKRGR40KK",
    "availability": {
      "console": true,
      "pc": true
    }
  },
  {
    "id": "9NBLGGH4PBBM",
    "name": "Gears of War 4",
    "url": "https://www.xbox.com/en-us/games/gears-of-war-4",
    "availability": {
      "console": true,
      "pc": true
    }
  },
  {
    "id": "9NBLGGH3SHM5",
    "name": "Gears of War: Ultimate Edition for Windows 10",
    "url": "https://www.microsoft.com/en-us/store/p/gears-of-war-ultimate-edition-for-windows-10/9NBLGGH3SHM5",
    "availability": {
      "console": false,
      "pc": true
    }
  },
  {
    "id": "9PNJ8VXWQ8HN",
    "name": "Gears Tactics - Windows 10",
    "url": "https://www.microsoft.com/en-us/store/p/gears-tactics---windows-10/9PNJ8VXWQ8HN",
    "availability": {
      "console": false,
      "pc": true
    }
  },
  {
    "id": "9MXWKHJ3VZZH",
    "name": "Goat Simulator Windows 10",
    "url": "https://www.microsoft.com/en-us/store/p/goat-simulator-windows-10/9MXWKHJ3VZZH",
    "availability": {
      "console": false,
      "pc": true
    }
  },
  {
    "id": "9MVK5W0HMRP7",
    "name": "Golf With Your Friends",
    "url": "https://www.microsoft.com/en-us/store/p/golf-with-your-friends/9MVK5W0HMRP7",
    "availability": {
      "console": false,
      "pc": true
    }
  },
  {
    "id": "9PBM5VSZDW5C",
    "name": "GoNNER WIN10",
    "url": "https://www.microsoft.com/en-us/store/p/gonner-win10/9PBM5VSZDW5C",
    "availability": {
      "console": false,
      "pc": true
    }
  },
  {
    "id": "9NHHP2H0ZP98",
    "name": "Gris",
    "url": "https://www.microsoft.com/en-us/store/p/gris/9NHHP2H0ZP98",
    "availability": {
      "console": false,
      "pc": true
    }
  },
  {
    "id": "9PJTHRNVH62H",
    "name": "Grounded - Game Preview",
    "url": "https://www.microsoft.com/en-us/store/p/grounded---game-preview/9PJTHRNVH62H",
    "availability": {
      "console": true,
      "pc": true
    }
  },
  {
    "id": "9NVK1W7L093S",
    "name": "Guacamelee! 2",
    "url": "https://www.microsoft.com/en-us/store/p/guacamelee-2/9NVK1W7L093S",
    "availability": {
      "console": true,
      "pc": true
    }
  },
  {
    "id": "9P5739G419LD",
    "name": "Halo 2: Anniversary",
    "url": "https://www.microsoft.com/en-us/store/p/halo-2-anniversary/9P5739G419LD",
    "availability": {
      "console": false,
      "pc": true
    }
  },
  {
    "id": "9PGL2Z1H9M4R",
    "name": "Halo 3",
    "url": "https://www.microsoft.com/en-us/store/p/halo-3/9PGL2Z1H9M4R",
    "availability": {
      "console": false,
      "pc": true
    }
  },
  {
    "id": "9NBLGGH5WMKM",
    "name": "Halo Wars 2",
    "url": "https://www.microsoft.com/en-us/store/p/halo-wars-2/9NBLGGH5WMKM",
    "availability": {
      "console": false,
      "pc": true
    }
  },
  {
    "id": "9NBLGGH515BD",
    "name": "Halo Wars 2: Standard Edition",
    "url": "https://www.microsoft.com/en-us/store/p/halo-wars-2-standard-edition/9NBLGGH515BD",
    "availability": {
      "console": false,
      "pc": true
    }
  },
  {
    "id": "9NBLGGH5WLR0",
    "name": "Halo Wars: Definitive Edition (PC)",
    "url": "https://www.microsoft.com/en-us/store/p/halo-wars-definitive-edition-pc/9NBLGGH5WLR0",
    "availability": {
      "console": false,
      "pc": true
    }
  },
  {
    "id": "9NWQMVSB63N4",
    "name": "Halo: Combat Evolved Anniversary",
    "url": "https://www.microsoft.com/en-us/store/p/halo-combat-evolved-anniversary/9NWQMVSB63N4",
    "availability": {
      "console": false,
      "pc": true
    }
  },
  {
    "id": "9N9WZT3PJ27W",
    "name": "Halo: Reach",
    "url": "https://www.microsoft.com/en-us/store/p/halo-reach/9N9WZT3PJ27W",
    "availability": {
      "console": false,
      "pc": true
    }
  },
  {
    "id": "9WZDNCRFHWFH",
    "name": "Halo: Spartan Assault",
    "url": "https://www.microsoft.com/en-us/store/p/halo-spartan-assault/9WZDNCRFHWFH",
    "availability": {
      "console": false,
      "pc": true
    }
  },
  {
    "id": "9WZDNCRFJBFJ",
    "name": "Halo: Spartan Strike",
    "url": "https://www.microsoft.com/en-us/store/p/halo-spartan-strike/9WZDNCRFJBFJ",
    "availability": {
      "console": false,
      "pc": true
    }
  },
  {
    "id": "9NTM9HXNLSZX",
    "name": "Halo: The Master Chief Collection",
    "url": "https://www.microsoft.com/en-us/store/p/halo-the-master-chief-collection/9NTM9HXNLSZX",
    "availability": {
      "console": false,
      "pc": true
    }
  },
  {
    "id": "9NCPXWLM4152",
    "name": "Hatoful Boyfriend",
    "url": "https://www.microsoft.com/en-us/store/p/hatoful-boyfriend/9NCPXWLM4152",
    "availability": {
      "console": false,
      "pc": true
    }
  },
  {
    "id": "9NF6WPNS1S73",
    "name": "Hearts of Iron IV: Cadet Edition",
    "url": "https://www.microsoft.com/en-us/store/p/hearts-of-iron-iv-cadet-edition/9NF6WPNS1S73",
    "availability": {
      "console": false,
      "pc": true
    }
  },
  {
    "id": "9NCLP4LV5K7Z",
    "name": "Hellblade: Senua's Sacrifice",
    "url": "https://www.microsoft.com/en-us/store/p/hellblade-senuas-sacrifice/9NCLP4LV5K7Z",
    "availability": {
      "console": false,
      "pc": true
    }
  },
  {
    "id": "9NDDH3R9DF40",
    "name": "Hello Neighbor",
    "url": "https://www.microsoft.com/en-us/store/p/hello-neighbor/9NDDH3R9DF40",
    "availability": {
      "console": false,
      "pc": true
    }
  },
  {
    "id": "9PKM22F7C9K5",
    "name": "Hollow Knight",
    "url": "https://www.microsoft.com/en-us/store/p/hollow-knight/9PKM22F7C9K5",
    "availability": {
      "console": false,
      "pc": true
    }
  },
  {
    "id": "9PPCS86WS28Z",
    "name": "Hotline Miami",
    "url": "https://www.microsoft.com/en-us/store/p/hotline-miami/9PPCS86WS28Z",
    "availability": {
      "console": false,
      "pc": true
    }
  },
  {
    "id": "9MT4HS1CP72W",
    "name": "Human Fall Flat",
    "url": "https://www.microsoft.com/en-us/store/p/human-fall-flat/9MT4HS1CP72W",
    "availability": {
      "console": false,
      "pc": true
    }
  },
  {
    "id": "9NVVJ8TBD7KP",
    "name": "HyperDot",
    "url": "https://www.microsoft.com/en-us/store/p/hyperdot/9NVVJ8TBD7KP",
    "availability": {
      "console": true,
      "pc": true
    }
  },
  {
    "id": "9PM3NVB3PXG0",
    "name": "Hypnospace Outlaw",
    "url": "https://www.microsoft.com/en-us/store/p/hypnospace-outlaw/9PM3NVB3PXG0",
    "availability": {
      "console": true,
      "pc": true
    }
  },
  {
    "id": "9N3KCLT53VDZ",
    "name": "Indivisible",
    "url": "https://www.microsoft.com/en-us/store/p/indivisible/9N3KCLT53VDZ",
    "availability": {
      "console": false,
      "pc": true
    }
  },
  {
    "id": "9NHGM9CS3XLF",
    "name": "Infinifactory",
    "url": "https://www.microsoft.com/en-us/store/p/infinifactory/9NHGM9CS3XLF",
    "availability": {
      "console": false,
      "pc": true
    }
  },
  {
    "id": "9PFW68JLS81F",
    "name": "It Lurks Below",
    "url": "https://www.microsoft.com/en-us/store/p/it-lurks-below/9PFW68JLS81F",
    "availability": {
      "console": true,
      "pc": true
    }
  },
  {
    "id": "9NBLGGH51BMC",
    "name": "Killer Instinct: Definitive Edition",
    "url": "https://www.microsoft.com/en-us/store/p/killer-instinct-definitive-edition/9NBLGGH51BMC",
    "availability": {
      "console": false,
      "pc": true
    }
  },
  {
    "id": "9PJZBB8FWK8H",
    "name": "Levelhead",
    "url": "https://www.microsoft.com/en-us/store/p/levelhead/9PJZBB8FWK8H",
    "availability": {
      "console": true,
      "pc": true
    }
  },
  {
    "id": "9MV6MCVLT8GR",
    "name": "Lonely Mountains: Downhill",
    "url": "https://www.microsoft.com/en-us/store/p/lonely-mountains-downhill/9MV6MCVLT8GR",
    "availability": {
      "console": true,
      "pc": true
    }
  },
  {
    "id": "9N83GKZLC8BK",
    "name": "Machinarium",
    "url": "https://www.microsoft.com/en-us/store/p/machinarium/9N83GKZLC8BK",
    "availability": {
      "console": false,
      "pc": true
    }
  },
  {
    "id": "9PGSCB1X2P7G",
    "name": "MARVEL VS. CAPCOM: INFINITE",
    "url": "https://www.microsoft.com/en-us/store/p/marvel-vs-capcom-infinite/9PGSCB1X2P7G",
    "availability": {
      "console": true,
      "pc": true
    }
  },
  {
    "id": "9PB86W3JK8Z5",
    "name": "MechWarrior 5: Mercenaries",
    "url": "https://www.microsoft.com/en-us/store/p/mechwarrior-5-mercenaries/9PB86W3JK8Z5",
    "availability": {
      "console": false,
      "pc": true
    }
  },
  {
    "id": "9NQ387M27TMV",
    "name": "Metro 2033 Redux",
    "url": "https://www.microsoft.com/en-us/store/p/metro-2033-redux/9NQ387M27TMV",
    "availability": {
      "console": false,
      "pc": true
    }
  },
  {
    "id": "9NM5W1TDNQZ3",
    "name": "Metro: Last Light Redux",
    "url": "https://www.microsoft.com/en-us/store/p/metro-last-light-redux/9NM5W1TDNQZ3",
    "availability": {
      "console": false,
      "pc": true
    }
  },
  {
    "id": "9NXN8GF8N9HT",
    "name": "Microsoft Flight Simulator: Standard",
    "url": "https://www.microsoft.com/en-us/store/p/microsoft-flight-simulator-standard/9NXN8GF8N9HT",
    "availability": {
      "console": false,
      "pc": true
    }
  },
  {
    "id": "9PDV8FKWP3B4",
    "name": "Middle-earth™: Shadow of War™",
    "url": "https://www.xbox.com/en-us/games/middle-earth-shadow-of-war",
    "availability": {
      "console": true,
      "pc": true
    }
  },
  {
    "id": "9P8MK4NC0LJB",
    "name": "Minecraft Dungeons - Windows 10",
    "url": "https://www.microsoft.com/en-us/store/p/minecraft-dungeons---windows-10/9P8MK4NC0LJB",
    "availability": {
      "console": false,
      "pc": true
    }
  },
  {
    "id": "9PJR1F15JBX0",
    "name": "Minit",
    "url": "https://www.microsoft.com/en-us/store/p/minit/9PJR1F15JBX0",
    "availability": {
      "console": false,
      "pc": true
    }
  },
  {
    "id": "9P8K66J3CQ9S",
    "name": "MISTOVER",
    "url": "https://www.microsoft.com/en-us/store/p/mistover/9P8K66J3CQ9S",
    "availability": {
      "console": false,
      "pc": true
    }
  },
  {
    "id": "9NZL00LF4V58",
    "name": "Momodora: Reverie Under the Moonlight",
    "url": "https://www.microsoft.com/en-us/store/p/momodora-reverie-under-the-moonlight/9NZL00LF4V58",
    "availability": {
      "console": false,
      "pc": true
    }
  },
  {
    "id": "9P8XJRLCLH2P",
    "name": "Moonlighter",
    "url": "https://www.microsoft.com/en-us/store/p/moonlighter/9P8XJRLCLH2P",
    "availability": {
      "console": true,
      "pc": true
    }
  },
  {
    "id": "9NVFHBKDLPM4",
    "name": "Mother Russia Bleeds",
    "url": "https://www.microsoft.com/en-us/store/p/mother-russia-bleeds/9NVFHBKDLPM4",
    "availability": {
      "console": false,
      "pc": true
    }
  },
  {
    "id": "9N9H593X8SVP",
    "name": "Moving Out",
    "url": "https://www.microsoft.com/en-us/store/p/moving-out/9N9H593X8SVP",
    "availability": {
      "console": false,
      "pc": true
    }
  },
  {
    "id": "9N58J0GM9MRP",
    "name": "MudRunner",
    "url": "https://www.microsoft.com/en-us/store/p/mudrunner/9N58J0GM9MRP",
    "availability": {
      "console": false,
      "pc": true
    }
  },
  {
    "id": "9N80L1CTZ86W",
    "name": "Munchkin: Quacked Quest",
    "url": "https://www.microsoft.com/en-us/store/p/munchkin-quacked-quest/9N80L1CTZ86W",
    "availability": {
      "console": true,
      "pc": true
    }
  },
  {
    "id": "9NMP9B9KMKLF",
    "name": "Mutant Year Zero: Road to Eden",
    "url": "https://www.microsoft.com/en-us/store/p/mutant-year-zero-road-to-eden/9NMP9B9KMKLF",
    "availability": {
      "console": true,
      "pc": true
    }
  },
  {
    "id": "9NMH293554QQ",
    "name": "My Friend Pedro Win10",
    "url": "https://www.microsoft.com/en-us/store/p/my-friend-pedro-win10/9NMH293554QQ",
    "availability": {
      "console": false,
      "pc": true
    }
  },
  {
    "id": "9NBLSN1JP7TH",
    "name": "My Time At Portia",
    "url": "https://www.microsoft.com/en-us/store/p/my-time-at-portia/9NBLSN1JP7TH",
    "availability": {
      "console": false,
      "pc": true
    }
  },
  {
    "id": "9PLWSGHFQ4PS",
    "name": "Neon Abyss",
    "url": "https://www.microsoft.com/en-us/store/p/neon-abyss/9PLWSGHFQ4PS",
    "availability": {
      "console": false,
      "pc": true
    }
  },
  {
    "id": "9MZN3SMXN824",
    "name": "New Super Lucky's Tale",
    "url": "https://www.microsoft.com/en-us/store/p/new-super-luckys-tale/9MZN3SMXN824",
    "availability": {
      "console": true,
      "pc": true
    }
  },
  {
    "id": "9N5KSQG0R9TB",
    "name": "Night Call",
    "url": "https://www.microsoft.com/en-us/store/p/night-call/9N5KSQG0R9TB",
    "availability": {
      "console": false,
      "pc": true
    }
  },
  {
    "id": "BQVQTL3PCH05",
    "name": "No Man's Sky",
    "url": "https://www.microsoft.com/en-us/store/p/no-mans-sky/BQVQTL3PCH05",
    "availability": {
      "console": true,
      "pc": true
    }
  },
  {
    "id": "9P01NRSZCVR6",
    "name": "Nowhere Prophet",
    "url": "https://www.microsoft.com/en-us/store/p/nowhere-prophet/9P01NRSZCVR6",
    "availability": {
      "console": true,
      "pc": true
    }
  },
  {
    "id": "9PBLH1322GX0",
    "name": "Observation",
    "url": "https://www.microsoft.com/en-us/store/p/observation/9PBLH1322GX0",
    "availability": {
      "console": true,
      "pc": true
    }
  },
  {
    "id": "9NBLGGH1Z6FB",
    "name": "Ori and the Blind Forest: Definitive Edition",
    "url": "https://www.microsoft.com/en-us/store/p/ori-and-the-blind-forest-definitive-edition/9NBLGGH1Z6FB",
    "availability": {
      "console": false,
      "pc": true
    }
  },
  {
    "id": "9N8CD0XZKLP4",
    "name": "Ori and the Will of the Wisps",
    "url": "https://www.xbox.com/en-us/games/ori-will-of-the-wisps",
    "availability": {
      "console": true,
      "pc": true
    }
  },
  {
    "id": "9NNW9V8DVPG6",
    "name": "Out of the Park Baseball 21",
    "url": "https://www.microsoft.com/en-us/store/p/out-of-the-park-baseball-21/9NNW9V8DVPG6",
    "availability": {
      "console": false,
      "pc": true
    }
  },
  {
    "id": "9PGB72NFG5JN",
    "name": "Overcooked! 2",
    "url": "https://www.microsoft.com/en-us/store/p/overcooked-2/9PGB72NFG5JN",
    "availability": {
      "console": false,
      "pc": true
    }
  },
  {
    "id": "9NBLGGH6CTZ5",
    "name": "Oxenfree",
    "url": "https://www.microsoft.com/en-us/store/p/oxenfree/9NBLGGH6CTZ5",
    "availability": {
      "console": false,
      "pc": true
    }
  },
  {
    "id": "9P8Q4W21QQZ2",
    "name": "Pandemic: The Board Game",
    "url": "https://www.microsoft.com/en-us/store/p/pandemic-the-board-game/9P8Q4W21QQZ2",
    "availability": {
      "console": true,
      "pc": true
    }
  },
  {
    "id": "9PHS5Q7KQMJM",
    "name": "Pathologic 2",
    "url": "https://www.microsoft.com/en-us/store/p/pathologic-2/9PHS5Q7KQMJM",
    "availability": {
      "console": true,
      "pc": true
    }
  },
  {
    "id": "9P1P5Q3BNM7J",
    "name": "Phoenix Point",
    "url": "https://www.microsoft.com/en-us/store/p/phoenix-point/9P1P5Q3BNM7J",
    "availability": {
      "console": false,
      "pc": true
    }
  },
  {
    "id": "9N8QNKN5ZKTH",
    "name": "Pikuniku Win10",
    "url": "https://www.microsoft.com/en-us/store/p/pikuniku-win10/9N8QNKN5ZKTH",
    "availability": {
      "console": false,
      "pc": true
    }
  },
  {
    "id": "9P5LZC1KB48V",
    "name": "Pillars of Eternity: Hero Edition",
    "url": "https://www.microsoft.com/en-us/store/p/pillars-of-eternity-hero-edition/9P5LZC1KB48V",
    "availability": {
      "console": false,
      "pc": true
    }
  },
  {
    "id": "9MWBPSQ5PKQR",
    "name": "Plebby Quest: The Crusades",
    "url": "https://www.microsoft.com/en-us/store/p/plebby-quest-the-crusades/9MWBPSQ5PKQR",
    "availability": {
      "console": false,
      "pc": true
    }
  },
  {
    "id": "9P5VMG8D4P4B",
    "name": "Power Rangers: Battle for the Grid",
    "url": "https://www.microsoft.com/en-us/store/p/power-rangers-battle-for-the-grid/9P5VMG8D4P4B",
    "availability": {
      "console": true,
      "pc": true
    }
  },
  {
    "id": "9P2J7WHV0K4N",
    "name": "RAGE 2 (PC)",
    "url": "https://www.microsoft.com/en-us/store/p/rage-2-pc/9P2J7WHV0K4N",
    "availability": {
      "console": false,
      "pc": true
    }
  },
  {
    "id": "9NBLGGH1Z6FQ",
    "name": "ReCore",
    "url": "https://www.microsoft.com/en-us/store/p/recore/9NBLGGH1Z6FQ",
    "availability": {
      "console": true,
      "pc": true
    }
  },
  {
    "id": "9NB2WLSJ2QK3",
    "name": "Reigns: Game of Thrones",
    "url": "https://www.microsoft.com/en-us/store/p/reigns-game-of-thrones/9NB2WLSJ2QK3",
    "availability": {
      "console": false,
      "pc": true
    }
  },
  {
    "id": "9NS84HCWZD8B",
    "name": "Rise of Nations: Extended Edition",
    "url": "https://www.microsoft.com/en-us/store/p/rise-of-nations-extended-edition/9NS84HCWZD8B",
    "availability": {
      "console": false,
      "pc": true
    }
  },
  {
    "id": "9P3PL76N0KWZ",
    "name": "Rush: A DisneyPixar Adventure",
    "url": "https://www.microsoft.com/en-us/store/p/rush-a-disneypixar-adventure/9P3PL76N0KWZ",
    "availability": {
      "console": true,
      "pc": true
    }
  },
  {
    "id": "9NFVLZQDZHKW",
    "name": "Saints Row IV: Re-Elected",
    "url": "https://www.microsoft.com/en-us/store/p/saints-row-iv-re-elected/9NFVLZQDZHKW",
    "availability": {
      "console": false,
      "pc": true
    }
  },
  {
    "id": "9NXPV1T3WS34",
    "name": "ScourgeBringer (Game Preview)",
    "url": "https://www.microsoft.com/en-us/store/p/scourgebringer-game-preview/9NXPV1T3WS34",
    "availability": {
      "console": false,
      "pc": true
    }
  },
  {
    "id": "9P2N57MC619K",
    "name": "Sea of Thieves",
    "url": "https://www.microsoft.com/en-us/store/p/sea-of-thieves/9P2N57MC619K",
    "availability": {
      "console": true,
      "pc": true
    }
  },
  {
    "id": "9NXQ4PX4TZJZ",
    "name": "Sea Salt",
    "url": "https://www.microsoft.com/en-us/store/p/sea-salt/9NXQ4PX4TZJZ",
    "availability": {
      "console": true,
      "pc": true
    }
  },
  {
    "id": "9P6SFBR1TCWQ",
    "name": "Shadow Warrior 2",
    "url": "https://www.microsoft.com/en-us/store/p/shadow-warrior-2/9P6SFBR1TCWQ",
    "availability": {
      "console": false,
      "pc": true
    }
  },
  {
    "id": "9MZQR8317S3B",
    "name": "Slay The Spire",
    "url": "https://www.microsoft.com/en-us/store/p/slay-the-spire/9MZQR8317S3B",
    "availability": {
      "console": false,
      "pc": true
    }
  },
  {
    "id": "9NG5L58FD3X5",
    "name": "Spiritfarer®",
    "url": "https://www.microsoft.com/en-us/store/p/spiritfarer/9NG5L58FD3X5",
    "availability": {
      "console": true,
      "pc": true
    }
  },
  {
    "id": "9NT4X7P8B9NB",
    "name": "State of Decay 2: Juggernaut Edition",
    "url": "https://www.xbox.com/en-us/games/state-of-decay-2",
    "availability": {
      "console": true,
      "pc": true
    }
  },
  {
    "id": "9PL8ST9QV6RP",
    "name": "State of Mind PC",
    "url": "https://www.microsoft.com/en-us/store/p/state-of-mind-pc/9PL8ST9QV6RP",
    "availability": {
      "console": false,
      "pc": true
    }
  },
  {
    "id": "9NXQPGMR917R",
    "name": "Stellaris",
    "url": "https://www.microsoft.com/en-us/store/p/stellaris/9NXQPGMR917R",
    "availability": {
      "console": false,
      "pc": true
    }
  },
  {
    "id": "9PMDDQ228FQD",
    "name": "Stranger Things 3: The Game",
    "url": "https://www.microsoft.com/en-us/store/p/stranger-things-3-the-game/9PMDDQ228FQD",
    "availability": {
      "console": false,
      "pc": true
    }
  },
  {
    "id": "9N7H54KNCB9N",
    "name": "Streets of Rage 4",
    "url": "https://www.microsoft.com/en-us/store/p/streets-of-rage-4/9N7H54KNCB9N",
    "availability": {
      "console": true,
      "pc": true
    }
  },
  {
    "id": "BX3S1Q5DVHRD",
    "name": "Subnautica",
    "url": "https://www.microsoft.com/en-us/store/p/subnautica/BX3S1Q5DVHRD",
    "availability": {
      "console": true,
      "pc": true
    }
  },
  {
    "id": "9NNLBL0T2Z43",
    "name": "Sunset Overdrive",
    "url": "https://www.microsoft.com/en-us/store/p/sunset-overdrive/9NNLBL0T2Z43",
    "availability": {
      "console": false,
      "pc": true
    }
  },
  {
    "id": "9PLMGFWCFZ9G",
    "name": "Super Lucky's Tale",
    "url": "https://www.microsoft.com/en-us/store/p/super-luckys-tale/9PLMGFWCFZ9G",
    "availability": {
      "console": false,
      "pc": true
    }
  },
  {
    "id": "9MXB71Q4VWGJ",
    "name": "Surviving Mars",
    "url": "https://www.microsoft.com/en-us/store/p/surviving-mars/9MXB71Q4VWGJ",
    "availability": {
      "console": false,
      "pc": true
    }
  },
  {
    "id": "9P4WKZXWP1QW",
    "name": "Tacoma",
    "url": "https://www.microsoft.com/en-us/store/p/tacoma/9P4WKZXWP1QW",
    "availability": {
      "console": true,
      "pc": true
    }
  },
  {
    "id": "9NBL0XKVCN5L",
    "name": "Tell Me Why",
    "url": "https://www.microsoft.com/en-us/store/p/tell-me-why/9NBL0XKVCN5L",
    "availability": {
      "console": false,
      "pc": true
    }
  },
  {
    "id": "9NF83PRZK6K3",
    "name": "Tell Me Why: Chapters 1-3",
    "url": "https://www.microsoft.com/en-us/store/p/tell-me-why-chapters-1-3/9NF83PRZK6K3",
    "availability": {
      "console": true,
      "pc": true
    }
  },
  {
    "id": "9PN3VDFTB5HZ",
    "name": "The Bard's Tale ARPG : Remastered and Resnarkled",
    "url": "https://www.microsoft.com/en-us/store/p/the-bards-tale-arpg--remastered-and-resnarkled/9PN3VDFTB5HZ",
    "availability": {
      "console": true,
      "pc": true
    }
  },
  {
    "id": "C2B4T86TXLRS",
    "name": "The Bard's Tale IV: Director's Cut",
    "url": "https://www.xbox.com/en-us/games/bards-tale-iv-directors-cut",
    "availability": {
      "console": true,
      "pc": true
    }
  },
  {
    "id": "9MVN4ND41DD3",
    "name": "The Bard's Tale Trilogy",
    "url": "https://www.microsoft.com/en-us/store/p/the-bards-tale-trilogy/9MVN4ND41DD3",
    "availability": {
      "console": true,
      "pc": true
    }
  },
  {
    "id": "9P4Z4TW66LPV",
    "name": "The Gardens Between",
    "url": "https://www.microsoft.com/en-us/store/p/the-gardens-between/9P4Z4TW66LPV",
    "availability": {
      "console": true,
      "pc": true
    }
  },
  {
    "id": "9NFKN56ZBMR0",
    "name": "The Long Dark",
    "url": "https://www.microsoft.com/en-us/store/p/the-long-dark/9NFKN56ZBMR0",
    "availability": {
      "console": false,
      "pc": true
    }
  },
  {
    "id": "9NCP1745JF7B",
    "name": "The Lord of the Rings: Adventure Card Game - Definitive Edition",
    "url": "https://www.microsoft.com/en-us/store/p/the-lord-of-the-rings-adventure-card-game---definitive-edition/9NCP1745JF7B",
    "availability": {
      "console": true,
      "pc": true
    }
  },
  {
    "id": "9NNFBW3NGV9K",
    "name": "The Messenger",
    "url": "https://www.microsoft.com/en-us/store/p/the-messenger/9NNFBW3NGV9K",
    "availability": {
      "console": false,
      "pc": true
    }
  },
  {
    "id": "9MWD2Z8L1FBQ",
    "name": "The Outer Worlds",
    "url": "https://www.microsoft.com/en-us/store/p/the-outer-worlds/9MWD2Z8L1FBQ",
    "availability": {
      "console": false,
      "pc": true
    }
  },
  {
    "id": "9PFHBH19RL3C",
    "name": "The Red Strings Club",
    "url": "https://www.microsoft.com/en-us/store/p/the-red-strings-club/9PFHBH19RL3C",
    "availability": {
      "console": false,
      "pc": true
    }
  },
  {
    "id": "9NLDM4DGX41G",
    "name": "The Surge 2 - Windows 10",
    "url": "https://www.microsoft.com/en-us/store/p/the-surge-2---windows-10/9NLDM4DGX41G",
    "availability": {
      "console": false,
      "pc": true
    }
  },
  {
    "id": "9N02KMVCRSRM",
    "name": "The Talos Principle",
    "url": "https://www.microsoft.com/en-us/store/p/the-talos-principle/9N02KMVCRSRM",
    "availability": {
      "console": false,
      "pc": true
    }
  },
  {
    "id": "9N9W1JK1X5QJ",
    "name": "The Touryst",
    "url": "https://www.microsoft.com/en-us/store/p/the-touryst/9N9W1JK1X5QJ",
    "availability": {
      "console": true,
      "pc": true
    }
  },
  {
    "id": "9NBLGGH4VVTL",
    "name": "The Turing Test",
    "url": "https://www.microsoft.com/en-us/store/p/the-turing-test/9NBLGGH4VVTL",
    "availability": {
      "console": false,
      "pc": true
    }
  },
  {
    "id": "9PHV10KXLJZT",
    "name": "Thumper",
    "url": "https://www.microsoft.com/en-us/store/p/thumper/9PHV10KXLJZT",
    "availability": {
      "console": false,
      "pc": true
    }
  },
  {
    "id": "9PJZXCCK7VLW",
    "name": "Ticket to Ride",
    "url": "https://www.microsoft.com/en-us/store/p/ticket-to-ride/9PJZXCCK7VLW",
    "availability": {
      "console": true,
      "pc": true
    }
  },
  {
    "id": "9NC0071DJ6XC",
    "name": "Torment: Tides of Numenera",
    "url": "https://www.microsoft.com/en-us/store/p/torment-tides-of-numenera/9NC0071DJ6XC",
    "availability": {
      "console": false,
      "pc": true
    }
  },
  {
    "id": "9PC4RWP34M2D",
    "name": "Totally Accurate Battle Simulator (Game Preview)",
    "url": "https://www.microsoft.com/en-us/store/p/totally-accurate-battle-simulator-game-preview/9PC4RWP34M2D",
    "availability": {
      "console": true,
      "pc": true
    }
  },
  {
    "id": "9NBM23T6G6RN",
    "name": "Tracks - The Train Set Game",
    "url": "https://www.microsoft.com/en-us/store/p/tracks---the-train-set-game/9NBM23T6G6RN",
    "availability": {
      "console": false,
      "pc": true
    }
  },
  {
    "id": "9NSFGM8J6MBJ",
    "name": "Trailmakers",
    "url": "https://www.microsoft.com/en-us/store/p/trailmakers/9NSFGM8J6MBJ",
    "availability": {
      "console": true,
      "pc": true
    }
  },
  {
    "id": "9PMT49X8ZGM2",
    "name": "Train Sim World® 2020",
    "url": "https://www.microsoft.com/en-us/store/p/train-sim-world-2020/9PMT49X8ZGM2",
    "availability": {
      "console": false,
      "pc": true
    }
  },
  {
    "id": "9N08S5VPC4SX",
    "name": "Two Point Hospital™",
    "url": "https://www.microsoft.com/en-us/store/p/two-point-hospital/9N08S5VPC4SX",
    "availability": {
      "console": false,
      "pc": true
    }
  },
  {
    "id": "9N52CQMFH3BB",
    "name": "UnderMine",
    "url": "https://www.microsoft.com/en-us/store/p/undermine/9N52CQMFH3BB",
    "availability": {
      "console": true,
      "pc": true
    }
  },
  {
    "id": "9N171CGFVT1L",
    "name": "Vambrace: Cold Soul",
    "url": "https://www.microsoft.com/en-us/store/p/vambrace-cold-soul/9N171CGFVT1L",
    "availability": {
      "console": true,
      "pc": true
    }
  },
  {
    "id": "9PJ1CGLKQSWS",
    "name": "Void Bastards",
    "url": "https://www.microsoft.com/en-us/store/p/void-bastards/9PJ1CGLKQSWS",
    "availability": {
      "console": false,
      "pc": true
    }
  },
  {
    "id": "9NJX558FNW9S",
    "name": "Wandersong",
    "url": "https://www.microsoft.com/en-us/store/p/wandersong/9NJX558FNW9S",
    "availability": {
      "console": false,
      "pc": true
    }
  },
  {
    "id": "9NRPTTJ94PCK",
    "name": "Wargroove",
    "url": "https://www.microsoft.com/en-us/store/p/wargroove/9NRPTTJ94PCK",
    "availability": {
      "console": true,
      "pc": true
    }
  },
  {
    "id": "C521HDXRTS7F",
    "name": "Wasteland 2: Director's Cut",
    "url": "https://www.microsoft.com/en-us/store/p/wasteland-2-directors-cut/C521HDXRTS7F",
    "availability": {
      "console": true,
      "pc": true
    }
  },
  {
    "id": "9NLT5XR52ZS7",
    "name": "Wasteland 3 (PC)",
    "url": "https://www.microsoft.com/en-us/store/p/wasteland-3-pc/9NLT5XR52ZS7",
    "availability": {
      "console": false,
      "pc": true
    }
  },
  {
    "id": "9NGH1FK0RJGL",
    "name": "Wasteland Remastered",
    "url": "https://www.microsoft.com/en-us/store/p/wasteland-remastered/9NGH1FK0RJGL",
    "availability": {
      "console": true,
      "pc": true
    }
  },
  {
    "id": "9NBLGGH5342P",
    "name": "We Happy Few",
    "url": "https://www.microsoft.com/en-us/store/p/we-happy-few/9NBLGGH5342P",
    "availability": {
      "console": false,
      "pc": true
    }
  },
  {
    "id": "9NV0540N4JRN",
    "name": "West of Dead",
    "url": "https://www.microsoft.com/en-us/store/p/west-of-dead/9NV0540N4JRN",
    "availability": {
      "console": false,
      "pc": true
    }
  },
  {
    "id": "9MZH0GG41HL9",
    "name": "Wizard of Legend",
    "url": "https://www.microsoft.com/en-us/store/p/wizard-of-legend/9MZH0GG41HL9",
    "availability": {
      "console": false,
      "pc": true
    }
  },
  {
    "id": "9PHFTS44F99K",
    "name": "Wolfenstein: Youngblood (PC)",
    "url": "https://www.microsoft.com/en-us/store/p/wolfenstein-youngblood-pc/9PHFTS44F99K",
    "availability": {
      "console": false,
      "pc": true
    }
  },
  {
    "id": "9N1FDTTSS49Z",
    "name": "WORLD OF HORROR (Game Preview)",
    "url": "https://www.microsoft.com/en-us/store/p/world-of-horror-game-preview/9N1FDTTSS49Z",
    "availability": {
      "console": false,
      "pc": true
    }
  },
  {
    "id": "9NVRZZJ4NG99",
    "name": "Worms W.M.D",
    "url": "https://www.microsoft.com/en-us/store/p/worms-wmd/9NVRZZJ4NG99",
    "availability": {
      "console": false,
      "pc": true
    }
  },
  {
    "id": "9PNBGZTL0Z1S",
    "name": "Xeno Crisis",
    "url": "https://www.microsoft.com/en-us/store/p/xeno-crisis/9PNBGZTL0Z1S",
    "availability": {
      "console": true,
      "pc": true
    }
  },
  {
    "id": "9PD0BJRBLRJM",
    "name": "Yakuza 0 for Windows 10",
    "url": "https://www.microsoft.com/en-us/store/p/yakuza-0-for-windows-10/9PD0BJRBLRJM",
    "availability": {
      "console": false,
      "pc": true
    }
  },
  {
    "id": "9MZNFNN3XJ3F",
    "name": "Yakuza Kiwami 2 for Windows 10",
    "url": "https://www.microsoft.com/en-us/store/p/yakuza-kiwami-2-for-windows-10/9MZNFNN3XJ3F",
    "availability": {
      "console": false,
      "pc": true
    }
  },
  {
    "id": "9P40SC5DQ9K0",
    "name": "Yakuza Kiwami for Windows 10",
    "url": "https://www.microsoft.com/en-us/store/p/yakuza-kiwami-for-windows-10/9P40SC5DQ9K0",
    "availability": {
      "console": false,
      "pc": true
    }
  },
  {
    "id": "9PJ06TZX4NMH",
    "name": "Zoo Tycoon: Ultimate Animal Collection",
    "url": "https://www.microsoft.com/en-us/store/p/zoo-tycoon-ultimate-animal-collection/9PJ06TZX4NMH",
    "availability": {
      "console": true,
      "pc": true
    }
  }
]
