{"errors":[],"warnings":[],"namedChunkGroups":{"polyfill":{"chunks":[2,0,7],"assets":["webpack-runtime-fd4945f9c48d84132c77.js","webpack-runtime-fd4945f9c48d84132c77.js.map","commons-f6cfb6c73ed4421d9007.js","commons-f6cfb6c73ed4421d9007.js.map","polyfill-30798f215e3d2888160f.js","polyfill-30798f215e3d2888160f.js.map"],"children":{},"childAssets":{}},"app":{"chunks":[2,6,0,3],"assets":["webpack-runtime-fd4945f9c48d84132c77.js","webpack-runtime-fd4945f9c48d84132c77.js.map","framework-b184e9a11f9b35f26f7b.js","framework-b184e9a11f9b35f26f7b.js.map","commons-f6cfb6c73ed4421d9007.js","commons-f6cfb6c73ed4421d9007.js.map","app-abd6710aef54d6d1c24f.js","app-abd6710aef54d6d1c24f.js.map"],"children":{},"childAssets":{}},"component---src-pages-games-tsx":{"chunks":[1,0,4],"assets":["styles.3deb5e37fbd9f45aa579.css","styles-e9d24b1846c7d6eb9685.js","styles-e9d24b1846c7d6eb9685.js.map","commons-f6cfb6c73ed4421d9007.js","commons-f6cfb6c73ed4421d9007.js.map","component---src-pages-games-tsx-7e60e59e930ce83a74a0.js","component---src-pages-games-tsx-7e60e59e930ce83a74a0.js.map"],"children":{},"childAssets":{}},"component---src-pages-index-tsx":{"chunks":[1,0,5],"assets":["styles.3deb5e37fbd9f45aa579.css","styles-e9d24b1846c7d6eb9685.js","styles-e9d24b1846c7d6eb9685.js.map","commons-f6cfb6c73ed4421d9007.js","commons-f6cfb6c73ed4421d9007.js.map","component---src-pages-index-tsx-68e277059807cc872b26.js","component---src-pages-index-tsx-68e277059807cc872b26.js.map"],"children":{},"childAssets":{}}},"assetsByChunkName":{"polyfill":["webpack-runtime-fd4945f9c48d84132c77.js","commons-f6cfb6c73ed4421d9007.js","polyfill-30798f215e3d2888160f.js"],"app":["webpack-runtime-fd4945f9c48d84132c77.js","framework-b184e9a11f9b35f26f7b.js","commons-f6cfb6c73ed4421d9007.js","app-abd6710aef54d6d1c24f.js"],"component---src-pages-games-tsx":["styles.3deb5e37fbd9f45aa579.css","styles-e9d24b1846c7d6eb9685.js","commons-f6cfb6c73ed4421d9007.js","component---src-pages-games-tsx-7e60e59e930ce83a74a0.js"],"component---src-pages-index-tsx":["styles.3deb5e37fbd9f45aa579.css","styles-e9d24b1846c7d6eb9685.js","commons-f6cfb6c73ed4421d9007.js","component---src-pages-index-tsx-68e277059807cc872b26.js"]}}